neurocache/__init__.py
neurocache/config.py
neurocache/embeddings.py
neurocache/memory.py
neurocache/storage.py
neurocache/utils.py
nuerocache-0.1.0.dist-info/licenses/LICENSE
nuerocache-0.1.0.dist-info/METADATA
nuerocache-0.1.0.dist-info/WHEEL
nuerocache-0.1.0.dist-info/top_level.txt
nuerocache-0.1.0.dist-info/RECORD
