Metadata-Version: 2.4
Name: NueroCache
Version: 0.1.0
Summary: AI memory system using embeddings
Author: Parker
License: MIT
License-File: LICENSE
Requires-Dist: chromadb
Requires-Dist: sentence-transformers
Dynamic: author
Dynamic: license-file
Dynamic: requires-dist
